{
    "model": "FeaturedItemsSection",
    "srcType": "git",
    "srcProjectId": "9a0364b9",
    "presets": [
        {
            "label": "Luft_Fahrzeuge",
            "locale": null,
            "metadata": {
                "categories": [
                    "Verein"
                ],
                "canDelete": true
            },
            "data": {
                "title": {
                    "$$type": "TitleBlock",
                    "text": "Fahrzeuge",
                    "color": "text-primary",
                    "styles": {
                        "self": {
                            "textAlign": "center"
                        }
                    }
                },
                "subtitle": "In unserem Verein gibt es nicht nur Flugzeuge. Wir benötigen auch normale Fahrzeugtechnik, um unsere Geräte, wie Flugzeuge und Winde, auf dem Flugplatz zu bewegen.",
                "items": [
                    {
                        "$$type": "FeaturedItem",
                        "title": "SKP - Startkontrollpunkt",
                        "tagline": "",
                        "subtitle": "Hier sitzt der Startleiter. Er hat das Sagen und sorgt für einen reibungsfreien Flugbetrieb.",
                        "text": "",
                        "image": {
                            "$$type": "ImageBlock",
                            "url": {
                                "$$ref": "stackbit_asset_id:static:public/images/SKP.jpg",
                                "$$type": "__asset_model"
                            },
                            "altText": "Placeholder Image",
                            "elementId": null,
                            "styles": {
                                "self": {
                                    "borderRadius": "x-large"
                                }
                            }
                        },
                        "actions": [],
                        "elementId": null,
                        "colors": "bg-light-fg-dark",
                        "styles": {
                            "self": {
                                "padding": [
                                    "pt-8",
                                    "pl-8",
                                    "pb-8",
                                    "pr-8"
                                ],
                                "borderRadius": "x-large",
                                "flexDirection": "col"
                            }
                        }
                    },
                    {
                        "$$type": "FeaturedItem",
                        "title": "Feuerwehr",
                        "tagline": "",
                        "subtitle": "This is the item subtitle",
                        "text": "\n\n",
                        "image": {
                            "$$type": "ImageBlock",
                            "url": {
                                "$$ref": "stackbit_asset_id:static:public/images/Feuerweher.jpg",
                                "$$type": "__asset_model"
                            },
                            "altText": "Placeholder image",
                            "elementId": null,
                            "styles": {
                                "self": {
                                    "borderRadius": "x-large"
                                }
                            }
                        },
                        "actions": [],
                        "elementId": null,
                        "colors": "bg-light-fg-dark",
                        "styles": {
                            "self": {
                                "padding": [
                                    "pt-8",
                                    "pl-8",
                                    "pb-8",
                                    "pr-8"
                                ],
                                "borderRadius": "x-large",
                                "flexDirection": "col"
                            }
                        }
                    },
                    {
                        "$$type": "FeaturedItem",
                        "title": "Winde",
                        "tagline": "",
                        "subtitle": "This is the item subtitle",
                        "text": "\n\n",
                        "image": {
                            "$$type": "ImageBlock",
                            "url": {
                                "$$ref": "stackbit_asset_id:static:public/images/Winde.jpg",
                                "$$type": "__asset_model"
                            },
                            "altText": "Placeholder image",
                            "elementId": null,
                            "styles": {
                                "self": {
                                    "borderRadius": "x-large"
                                }
                            }
                        },
                        "actions": [],
                        "elementId": null,
                        "colors": "bg-light-fg-dark",
                        "styles": {
                            "self": {
                                "padding": [
                                    "pt-8",
                                    "pl-8",
                                    "pb-8",
                                    "pr-8"
                                ],
                                "borderRadius": "x-large",
                                "flexDirection": "col"
                            }
                        }
                    },
                    {
                        "$$type": "FeaturedItem",
                        "title": "Großflächenmäher",
                        "tagline": "",
                        "subtitle": "John Deere Wam 1600",
                        "text": "",
                        "image": {
                            "$$type": "ImageBlock",
                            "url": {
                                "$$ref": "stackbit_asset_id:static:public/images/Wam.jpg",
                                "$$type": "__asset_model"
                            },
                            "altText": "Placeholder text",
                            "elementId": null,
                            "styles": {
                                "self": {
                                    "borderRadius": "x-large"
                                }
                            }
                        },
                        "actions": [],
                        "elementId": null,
                        "colors": "bg-light-fg-dark",
                        "styles": {
                            "self": {
                                "padding": [
                                    "pt-8",
                                    "pl-8",
                                    "pb-8",
                                    "pr-8"
                                ],
                                "borderRadius": "x-large",
                                "flexDirection": "col"
                            }
                        }
                    }
                ],
                "actions": [],
                "badge": null,
                "elementId": null,
                "variant": "small-list",
                "colors": "bg-light-fg-dark",
                "backgroundImage": null,
                "styles": {
                    "self": {
                        "padding": [
                            "pt-16",
                            "pl-8",
                            "pb-16",
                            "pr-8"
                        ],
                        "justifyContent": "center"
                    },
                    "subtitle": {
                        "textAlign": "center"
                    }
                }
            },
            "thumbnail": "images/featured-items-section-luft_fahrzeuge-06a9.png"
        }
    ]
}
